push_swap_gui/__init__.py
push_swap_gui/__main__.py
push_swap_gui/app_gui.py
push_swap_gui/game_info.py
push_swap_gui/push_swap_algo.py
push_swap_gui/push_swap_stacks.py
push_swap_gui-1.1.dist-info/LICENSE
push_swap_gui-1.1.dist-info/METADATA
push_swap_gui-1.1.dist-info/WHEEL
push_swap_gui-1.1.dist-info/entry_points.txt
push_swap_gui-1.1.dist-info/top_level.txt
push_swap_gui-1.1.dist-info/RECORD
