Metadata-Version: 2.1
Name: push-swap-gui
Version: 1.1
Summary: Implementation of push-swap (42-school project) on python with GUI.
Home-page: https://github.com/elijahkash/push_swap_gui
Author: Ilya Kashnitskiy
Author-email: elijahkash.code@gmail.com
License: MIT
Keywords: 42 push_swap push-swap
Platform: UNKNOWN
Classifier: Programming Language :: Python :: 3
Classifier: License :: OSI Approved :: MIT License
Classifier: Operating System :: OS Independent
Requires-Python: >=3.7
Requires-Dist: colour (>=0.1.5)
Requires-Dist: pyttk (>=0.3.2)
